BeginnersbookCYuyanShiliChuyiFix1/README.md
BeginnersbookCYuyanShiliChuyiFix1/__init__.py
BeginnersbookCYuyanShiliChuyiFix1/__main__.py
BeginnersbookCYuyanShiliChuyiFix1/file.epub
BeginnersbookCYuyanShiliChuyiFix1/index.html
BeginnersbookCYuyanShiliChuyiFix1/css/__init__.py
BeginnersbookCYuyanShiliChuyiFix1/css/annotations.css
BeginnersbookCYuyanShiliChuyiFix1/css/main.css
BeginnersbookCYuyanShiliChuyiFix1/css/normalize.css
BeginnersbookCYuyanShiliChuyiFix1/css/popup.css
BeginnersbookCYuyanShiliChuyiFix1/font/__init__.py
BeginnersbookCYuyanShiliChuyiFix1/font/fontello.eot
BeginnersbookCYuyanShiliChuyiFix1/font/fontello.svg
BeginnersbookCYuyanShiliChuyiFix1/font/fontello.ttf
BeginnersbookCYuyanShiliChuyiFix1/font/fontello.woff
BeginnersbookCYuyanShiliChuyiFix1/img/__init__.py
BeginnersbookCYuyanShiliChuyiFix1/img/annotator-glyph-sprite.png
BeginnersbookCYuyanShiliChuyiFix1/img/annotator-icon-sprite.png
BeginnersbookCYuyanShiliChuyiFix1/img/apple-touch-icon.png
BeginnersbookCYuyanShiliChuyiFix1/img/cancelfullscreen.png
BeginnersbookCYuyanShiliChuyiFix1/img/close.png
BeginnersbookCYuyanShiliChuyiFix1/img/fullscreen.png
BeginnersbookCYuyanShiliChuyiFix1/img/loader.gif
BeginnersbookCYuyanShiliChuyiFix1/img/menu-icon.png
BeginnersbookCYuyanShiliChuyiFix1/img/save.png
BeginnersbookCYuyanShiliChuyiFix1/img/saved.png
BeginnersbookCYuyanShiliChuyiFix1/img/settings-s.png
BeginnersbookCYuyanShiliChuyiFix1/img/settings.png
BeginnersbookCYuyanShiliChuyiFix1/img/star.png
BeginnersbookCYuyanShiliChuyiFix1/js/__init__.py
BeginnersbookCYuyanShiliChuyiFix1/js/epub.js
BeginnersbookCYuyanShiliChuyiFix1/js/epub.min.js
BeginnersbookCYuyanShiliChuyiFix1/js/epub.min.map
BeginnersbookCYuyanShiliChuyiFix1/js/hooks.min.js
BeginnersbookCYuyanShiliChuyiFix1/js/hooks.min.map
BeginnersbookCYuyanShiliChuyiFix1/js/reader.js
BeginnersbookCYuyanShiliChuyiFix1/js/reader.js.map
BeginnersbookCYuyanShiliChuyiFix1/js/reader.min.js
BeginnersbookCYuyanShiliChuyiFix1/js/reader.min.map
beginnersbook_c_yuyan_shili_chuyi_fix1-2025.3.23.0.dist-info/METADATA
beginnersbook_c_yuyan_shili_chuyi_fix1-2025.3.23.0.dist-info/WHEEL
beginnersbook_c_yuyan_shili_chuyi_fix1-2025.3.23.0.dist-info/entry_points.txt
beginnersbook_c_yuyan_shili_chuyi_fix1-2025.3.23.0.dist-info/top_level.txt
beginnersbook_c_yuyan_shili_chuyi_fix1-2025.3.23.0.dist-info/RECORD
